ao_killboard-0.1.2-py3.8-nspkg.pth
antze/ao_killboard.py
ao_killboard-0.1.2.dist-info/LICENSE
ao_killboard-0.1.2.dist-info/METADATA
ao_killboard-0.1.2.dist-info/WHEEL
ao_killboard-0.1.2.dist-info/entry_points.txt
ao_killboard-0.1.2.dist-info/namespace_packages.txt
ao_killboard-0.1.2.dist-info/top_level.txt
ao_killboard-0.1.2.dist-info/zip-safe
ao_killboard-0.1.2.dist-info/RECORD
