Metadata-Version: 2.1
Name: ao-killboard
Version: 0.1.2
Summary: A minimalistic Discord bot for Albion Online's killboard.
Home-page: https://github.com/antze-k/ao-killboard-py
Author: Antze K.
Author-email: unresolved-external@singu-lair.com
License: MIT
Project-URL: Source, https://github.com/antze-k/ao-killboard-py
Project-URL: Tracker, https://github.com/antze-k/ao-killboard-py/issues
Platform: any
Classifier: Topic :: Utilities
Classifier: Development Status :: 4 - Beta
Classifier: License :: OSI Approved :: MIT License
Classifier: Programming Language :: Python :: 3.6
Classifier: Programming Language :: Python :: 3.7
Classifier: Programming Language :: Python :: 3.8
Classifier: Programming Language :: Python :: 3.9
Classifier: Operating System :: OS Independent
Requires-Python: >=3.6
Requires-Dist: discord.py
Requires-Dist: httpx
Requires-Dist: python-dateutil
